cmap/__init__.py
cmap/_catalog.py
cmap/_color.py
cmap/_colormap.py
cmap/_external.py
cmap/_png.py
cmap/_util.py
cmap/py.typed
cmap/__pyinstaller/__init__.py
cmap/__pyinstaller/conftest.py
cmap/__pyinstaller/hook-cmap.py
cmap/__pyinstaller/test_cmap.py
cmap/data/__init__.py
cmap/data/bids/__init__.py
cmap/data/bids/record.json
cmap/data/chrisluts/record.json
cmap/data/cividis/__init__.py
cmap/data/cividis/record.json
cmap/data/cmap/record.json
cmap/data/cmasher/__init__.py
cmap/data/cmasher/record.json
cmap/data/cmocean/__init__.py
cmap/data/cmocean/algae.py
cmap/data/cmocean/amp.py
cmap/data/cmocean/balance.py
cmap/data/cmocean/curl.py
cmap/data/cmocean/deep.py
cmap/data/cmocean/delta.py
cmap/data/cmocean/dense.py
cmap/data/cmocean/diff.py
cmap/data/cmocean/haline.py
cmap/data/cmocean/ice.py
cmap/data/cmocean/matter.py
cmap/data/cmocean/oxy.py
cmap/data/cmocean/phase.py
cmap/data/cmocean/rain.py
cmap/data/cmocean/record.json
cmap/data/cmocean/solar.py
cmap/data/cmocean/speed.py
cmap/data/cmocean/tarn.py
cmap/data/cmocean/tempo.py
cmap/data/cmocean/thermal.py
cmap/data/cmocean/topo.py
cmap/data/cmocean/turbid.py
cmap/data/colorbrewer/__init__.py
cmap/data/colorbrewer/record.json
cmap/data/colorcet/CET_C1.py
cmap/data/colorcet/CET_C10.py
cmap/data/colorcet/CET_C11.py
cmap/data/colorcet/CET_C2.py
cmap/data/colorcet/CET_C3.py
cmap/data/colorcet/CET_C4.py
cmap/data/colorcet/CET_C5.py
cmap/data/colorcet/CET_C6.py
cmap/data/colorcet/CET_C7.py
cmap/data/colorcet/CET_C8.py
cmap/data/colorcet/CET_C9.py
cmap/data/colorcet/CET_CBC1.py
cmap/data/colorcet/CET_CBC2.py
cmap/data/colorcet/CET_CBD1.py
cmap/data/colorcet/CET_CBD2.py
cmap/data/colorcet/CET_CBL1.py
cmap/data/colorcet/CET_CBL2.py
cmap/data/colorcet/CET_CBL3.py
cmap/data/colorcet/CET_CBL4.py
cmap/data/colorcet/CET_CBTC1.py
cmap/data/colorcet/CET_CBTC2.py
cmap/data/colorcet/CET_CBTD1.py
cmap/data/colorcet/CET_CBTL1.py
cmap/data/colorcet/CET_CBTL2.py
cmap/data/colorcet/CET_CBTL3.py
cmap/data/colorcet/CET_CBTL4.py
cmap-0.6.2.dist-info/METADATA
cmap-0.6.2.dist-info/WHEEL
cmap-0.6.2.dist-info/entry_points.txt
cmap-0.6.2.dist-info/licenses/LICENSE/LICENSE
cmap-0.6.2.dist-info/licenses/LICENSE/LICENSE_CMASHER
cmap-0.6.2.dist-info/licenses/LICENSE/LICENSE_CMOCEAN
cmap-0.6.2.dist-info/licenses/LICENSE/LICENSE_COLORBREWER
cmap-0.6.2.dist-info/licenses/LICENSE/LICENSE_COLORCET
cmap-0.6.2.dist-info/licenses/LICENSE/LICENSE_CRAMERI
cmap-0.6.2.dist-info/licenses/LICENSE/LICENSE_CVIDIS
cmap-0.6.2.dist-info/licenses/LICENSE/LICENSE_GLASBEY
cmap-0.6.2.dist-info/licenses/LICENSE/LICENSE_TOL
cmap-0.6.2.dist-info/licenses/LICENSE/LICENSE_WISTIA
cmap-0.6.2.dist-info/licenses/LICENSE/LICENSE_YORICK
cmap-0.6.2.dist-info/RECORD
