Metadata-Version: 2.4
Name: cmap
Version: 0.6.2
Summary: Scientific colormaps for python, without dependencies
Project-URL: Homepage, https://github.com/pyapp-kit/cmap
Project-URL: Repository, https://github.com/pyapp-kit/cmap
Project-URL: Bug Tracker, https://github.com/pyapp-kit/cmap/issues
Project-URL: Documentation, https://cmap-docs.rtfd.io/
Author-email: Talley Lambert <talley.lambert@gmail.com>
License-Expression: BSD-3-Clause
License-File: LICENSE/LICENSE
License-File: LICENSE/LICENSE_CMASHER
License-File: LICENSE/LICENSE_CMOCEAN
License-File: LICENSE/LICENSE_COLORBREWER
License-File: LICENSE/LICENSE_COLORCET
License-File: LICENSE/LICENSE_CRAMERI
License-File: LICENSE/LICENSE_CVIDIS
License-File: LICENSE/LICENSE_GLASBEY
License-File: LICENSE/LICENSE_TOL
License-File: LICENSE/LICENSE_WISTIA
License-File: LICENSE/LICENSE_YORICK
Classifier: Development Status :: 4 - Beta
Classifier: License :: OSI Approved :: BSD License
Classifier: Programming Language :: Python :: 3
Classifier: Programming Language :: Python :: 3.9
Classifier: Programming Language :: Python :: 3.10
Classifier: Programming Language :: Python :: 3.11
Classifier: Programming Language :: Python :: 3.12
Classifier: Programming Language :: Python :: 3.13
Requires-Python: >=3.9
Requires-Dist: numpy
